feature_schema/__init__.py
feature_schema/core.py
feature_schema-0.1.5.dist-info/licenses/LICENSE
feature_schema-0.1.5.dist-info/METADATA
feature_schema-0.1.5.dist-info/WHEEL
feature_schema-0.1.5.dist-info/top_level.txt
feature_schema-0.1.5.dist-info/RECORD
